LICENSE
MANIFEST.in
README.md
setup.py
better_filter_widget/__init__.py
better_filter_widget/models.py
better_filter_widget/widgets.py
better_filter_widget/static/css/better-filter-widget.css
better_filter_widget/static/js/better-filter-widget.js
django_better_filter_widget.egg-info/PKG-INFO
django_better_filter_widget.egg-info/SOURCES.txt
django_better_filter_widget.egg-info/dependency_links.txt
django_better_filter_widget.egg-info/top_level.txt