Metadata-Version: 1.0
Name: django-better-filter-widget
Version: 0.2
Summary: UNKNOWN
Home-page: https://github.com/ExoticObjects/django-better-filter-widget
Author: Exotic Objects LLC
Author-email: git@extc.co
License: MIT
Platform: UNKNOWN
